gdbgui/SSLify.py
gdbgui/VERSION.txt
gdbgui/__init__.py
gdbgui/__main__.py
gdbgui/cli.py
gdbgui/htmllistformatter.py
gdbgui/py.typed
gdbgui/server/__init__.py
gdbgui/server/app.py
gdbgui/server/constants.py
gdbgui/server/http_routes.py
gdbgui/server/http_util.py
gdbgui/server/ptylib.py
gdbgui/server/server.py
gdbgui/server/sessionmanager.py
gdbgui/static/favicon.ico
gdbgui/static/css/gdbgui.css
gdbgui/static/css/splitjs-gdbgui.css
gdbgui/static/css/tailwind.css
gdbgui/static/images/github.jpg
gdbgui/static/images/paypal.svg
gdbgui/static/images/ploticon.png
gdbgui/static/images/ploticon_orig.png
gdbgui/static/images/twitter.png
gdbgui/static/js/dashboard.js
gdbgui/static/js/dashboard.js.map
gdbgui/static/js/main.js
gdbgui/static/js/main.js.map
gdbgui/static/vendor/css/animate.css
gdbgui/static/vendor/css/bootstrap.min.css
gdbgui/static/vendor/css/gdbgui_awesomeplete.css
gdbgui/static/vendor/css/pygments/emacs.css
gdbgui/static/vendor/css/pygments/light.css
gdbgui/static/vendor/css/pygments/monokai.css
gdbgui/static/vendor/css/pygments/vim.css
gdbgui/static/vendor/fonts/glyphicons-halflings-regular.woff2
gdbgui/static/vendor/images/splitjs/grips/horizontal.png
gdbgui/static/vendor/js/awesomeplete.min.js
gdbgui/static/vendor/js/bootstrap.min.js
gdbgui/static/vendor/js/jquery.flot-0.8.3.min.js
gdbgui/static/vendor/js/jquery.min.js
gdbgui/static/vendor/js/lodash.min.js
gdbgui/static/vendor/js/moment.min.js
gdbgui/static/vendor/js/socket.io-2.0.3.min.js
gdbgui/static/vendor/js/socket.io.js.map
gdbgui/static/vendor/js/splitjs.min-1.2.0.js
gdbgui/static/vendor/js/vis-4.20.1.min.js
gdbgui/templates/dashboard.html
gdbgui/templates/gdbgui.html
gdbgui-0.15.3.0.dist-info/licenses/LICENSE
gdbgui-0.15.3.0.dist-info/METADATA
gdbgui-0.15.3.0.dist-info/WHEEL
gdbgui-0.15.3.0.dist-info/entry_points.txt
gdbgui-0.15.3.0.dist-info/top_level.txt
gdbgui-0.15.3.0.dist-info/RECORD
